MANIFEST.in
README.md
setup.cfg
setup.py
ner_s2s/__init__.py
ner_s2s/deliver_utils.py
ner_s2s/utils.py
ner_s2s.egg-info/PKG-INFO
ner_s2s.egg-info/SOURCES.txt
ner_s2s.egg-info/dependency_links.txt
ner_s2s.egg-info/requires.txt
ner_s2s.egg-info/top_level.txt
ner_s2s/ner_estimator/__init__.py
ner_s2s/ner_estimator/estimator_run.py
ner_s2s/ner_estimator/input.py
ner_s2s/ner_estimator/model.py
ner_s2s/ner_estimator/train_model.py
ner_s2s/ner_estimator/algorithms/BiLSTM_CRF_lookup_model.py
ner_s2s/ner_estimator/algorithms/BiLSTM_CRF_model.py
ner_s2s/ner_estimator/algorithms/BiLSTM_CRF_ngram_model.py
ner_s2s/ner_estimator/algorithms/IDCNN_CRF_model.py
ner_s2s/ner_estimator/algorithms/Stacked_BiLSTM_CRF_model.py
ner_s2s/ner_estimator/algorithms/__init__.py
ner_s2s/ner_estimator/algorithms/lookup_model.py
ner_s2s/ner_estimator/algorithms/model.py
ner_s2s/ner_estimator/algorithms/ngram_model.py
ner_s2s/ner_estimator/metrics/__init__.py
ner_s2s/ner_keras/__init__.py
ner_s2s/ner_keras/data_preprocess.py
ner_s2s/ner_keras/input.py
ner_s2s/ner_keras/keras_run.py
ner_s2s/ner_keras_bert/__init__.py
ner_s2s/ner_keras_bert/input.py
ner_s2s/ner_keras_bert/run.py
ner_s2s/ner_keras_bert/utils.py
ner_s2s/preprocess_hooks/__init__.py
ner_s2s/preprocess_hooks/corpus_augment.py
ner_s2s/preprocess_hooks/corpus_drop.py
ner_s2s/preprocess_hooks/hook_base.py
ner_s2s/server/__init__.py
ner_s2s/server/http.py
ner_s2s/server/http_paddle.py
ner_s2s/server/legacy_http.py
ner_s2s/server/lookup_http.py
ner_s2s/server/ngram_http.py
ner_s2s/server/paddle_inference.py
ner_s2s/server/tensorflow_inference.py
ner_s2s/server/tensorflow_keras_h5_inference.py
ner_s2s/server/tensorflow_keras_savedmodel_inference.py
ner_s2s/server/inference/__init__.py
ner_s2s/server/inference/inference_base.py
ner_s2s/server/inference/keras_inference_base.py
ner_s2s/server/inference/tensorflow_inference.py
ner_s2s/server/inference/tensorflow_keras_h5_inference.py
ner_s2s/server/inference/tensorflow_keras_savedmodel_inference.py
ner_s2s/tf/__init__.py
ner_s2s/tf/python/__init__.py
ner_s2s/tf/python/keras/__init__.py
ner_s2s/tf/python/keras/activations.py