Metadata-Version: 1.0
Name: ner-s2s
Version: 0.0.3
Summary: ner_s2s
Home-page: https://github.com/shfshf/ner_s2s
Author: Hanfeng Song
Author-email: 1316478299@qq.com
License: Apache 2.0
Platform: UNKNOWN
